playwright_stealth/__init__.py
playwright_stealth/stealth.py
playwright_stealth/js/chrome.app.js
playwright_stealth/js/chrome.csi.js
playwright_stealth/js/chrome.hairline.js
playwright_stealth/js/chrome.load.times.js
playwright_stealth/js/chrome.runtime.js
playwright_stealth/js/generate.magic.arrays.js
playwright_stealth/js/iframe.contentWindow.js
playwright_stealth/js/media.codecs.js
playwright_stealth/js/navigator.hardwareConcurrency.js
playwright_stealth/js/navigator.languages.js
playwright_stealth/js/navigator.permissions.js
playwright_stealth/js/navigator.platform.js
playwright_stealth/js/navigator.plugins.js
playwright_stealth/js/navigator.userAgent.js
playwright_stealth/js/navigator.vendor.js
playwright_stealth/js/utils.js
playwright_stealth/js/webgl.vendor.js
playwright_stealth/js/window.outerdimensions.js
tests/__init__.py
tests/demo_persistent_test.py
tests/demo_with_stealth_test.py
tests/demo_without_stealth_test.py
playwright_stealth-1.0.6.dist-info/LICENSE
playwright_stealth-1.0.6.dist-info/METADATA
playwright_stealth-1.0.6.dist-info/WHEEL
playwright_stealth-1.0.6.dist-info/top_level.txt
playwright_stealth-1.0.6.dist-info/RECORD
