Metadata-Version: 2.1
Name: playwright-stealth
Version: 1.0.6
Summary: playwright stealth
Home-page: https://github.com/AtuboDad/playwright_stealth
Author: AtuboDad
Author-email: lcjasas@sina.com
Classifier: Programming Language :: Python :: 3
Classifier: License :: OSI Approved :: MIT License
Classifier: Operating System :: OS Independent
Requires-Python: >=3, !=3.0.*, !=3.1.*, !=3.2.*, !=3.3.*, !=3.4.*
Provides-Extra: test
License-File: LICENSE
